LICENSE
MANIFEST.in
README.md
setup.py
django_social_api.egg-info/PKG-INFO
django_social_api.egg-info/SOURCES.txt
django_social_api.egg-info/dependency_links.txt
django_social_api.egg-info/not-zip-safe
django_social_api.egg-info/requires.txt
django_social_api.egg-info/top_level.txt
social_api/__init__.py
social_api/__init__.pyc
social_api/api.py
social_api/api.pyc
social_api/exceptions.py
social_api/exceptions.pyc
social_api/lock.py
social_api/lock.pyc
social_api/testcase.py
social_api/tests.py
social_api/tests.pyc
social_api/utils.py
social_api/utils.pyc
social_api/storages/__init__.py
social_api/storages/__init__.pyc
social_api/storages/base.py
social_api/storages/base.pyc
social_api/storages/oauthtokens.py
social_api/storages/oauthtokens.pyc
social_api/storages/social_auth.py
social_api/storages/social_auth.pyc