Metadata-Version: 1.1
Name: django-social-api
Version: 0.1.1
Summary: Django social networks API abstraction layer
Home-page: https://github.com/ramusus/django-social-api
Author: ramusus
Author-email: ramusus@gmail.com
License: BSD
Download-URL: http://pypi.python.org/pypi/django-social-api
Platform: UNKNOWN
Classifier: Development Status :: 4 - Beta
Classifier: Environment :: Web Environment
Classifier: Intended Audience :: Developers
Classifier: License :: OSI Approved :: BSD License
Classifier: Operating System :: OS Independent
Classifier: Programming Language :: Python
Classifier: Topic :: Software Development :: Libraries :: Python Modules
